dumbee/__init__.py
dumbee/core/__init__.py
dumbee/core/driver.py
dumbee/core/engine.py
dumbee/core/middlewaring.py
dumbee/core/nodes.py
dumbee/core/query.py
dumbee/drivers/__init__.py
dumbee/drivers/filesystem.py
dumbee/ext/__init__.py
dumbee/ext/json/__init__.py
dumbee/ext/json/serialization.py
dumbee/ext/jsonschema/__init__.py
dumbee/ext/jsonschema/validation.py
dumbee/ext/logging/__init__.py
dumbee/ext/pydantic/__init__.py
dumbee/ext/pydantic/validation.py
tests/__init__.py
tests/main.py
dumbee-0.2.3.dist-info/METADATA
dumbee-0.2.3.dist-info/WHEEL
dumbee-0.2.3.dist-info/top_level.txt
dumbee-0.2.3.dist-info/RECORD
