Metadata-Version: 2.1
Name: dumbee
Version: 0.2.3
Summary: A dumb database, not for production
Home-page: https://github.com/dschenck/dumbee
Author: David Schenck
Author-email: david.schenck@outlook.com
Classifier: Programming Language :: Python :: 3
Classifier: License :: OSI Approved :: MIT License
Classifier: Operating System :: OS Independent
Requires-Dist: jsonschema
Requires-Dist: pydantic
Requires-Dist: filelock
